BCSFE_Python_Discord/__init__.py
BCSFE_Python_Discord/__main__.py
BCSFE_Python_Discord/adb_handler.py
BCSFE_Python_Discord/config_manager.py
BCSFE_Python_Discord/csv_handler.py
BCSFE_Python_Discord/feature_handler.py
BCSFE_Python_Discord/game_data_getter.py
BCSFE_Python_Discord/helper.py
BCSFE_Python_Discord/item.py
BCSFE_Python_Discord/locale_handler.py
BCSFE_Python_Discord/managed_item.py
BCSFE_Python_Discord/parse_save.py
BCSFE_Python_Discord/patcher.py
BCSFE_Python_Discord/py.typed
BCSFE_Python_Discord/root_handler.py
BCSFE_Python_Discord/serialise_save.py
BCSFE_Python_Discord/server_handler.py
BCSFE_Python_Discord/tracker.py
BCSFE_Python_Discord/updater.py
BCSFE_Python_Discord/user_input_handler.py
BCSFE_Python_Discord/edits/__init__.py
BCSFE_Python_Discord/edits/basic/__init__.py
BCSFE_Python_Discord/edits/basic/basic_items.py
BCSFE_Python_Discord/edits/basic/catfruit.py
BCSFE_Python_Discord/edits/basic/catseyes.py
BCSFE_Python_Discord/edits/basic/ototo_base_mats.py
BCSFE_Python_Discord/edits/basic/talent_orbs.py
BCSFE_Python_Discord/edits/basic/talent_orbs_new.py
BCSFE_Python_Discord/edits/cats/__init__.py
BCSFE_Python_Discord/edits/cats/cat_helper.py
BCSFE_Python_Discord/edits/cats/cat_id_selector.py
BCSFE_Python_Discord/edits/cats/chara_drop.py
BCSFE_Python_Discord/edits/cats/clear_cat_guide.py
BCSFE_Python_Discord/edits/cats/evolve_cats.py
BCSFE_Python_Discord/edits/cats/get_remove_cats.py
BCSFE_Python_Discord/edits/cats/talents.py
BCSFE_Python_Discord/edits/cats/upgrade_blue.py
BCSFE_Python_Discord/edits/cats/upgrade_cats.py
BCSFE_Python_Discord/edits/gamototo/__init__.py
BCSFE_Python_Discord/edits/gamototo/fix_gamatoto.py
BCSFE_Python_Discord/edits/gamototo/gamatoto_xp.py
BCSFE_Python_Discord/edits/gamototo/helpers.py
BCSFE_Python_Discord/edits/gamototo/ototo_cat_cannon.py
BCSFE_Python_Discord/edits/levels/__init__.py
BCSFE_Python_Discord/edits/levels/aku.py
BCSFE_Python_Discord/edits/levels/allow_filibuster_clearing.py
bcsfe_discord-2.7.59.dist-info/METADATA
bcsfe_discord-2.7.59.dist-info/WHEEL
bcsfe_discord-2.7.59.dist-info/top_level.txt
bcsfe_discord-2.7.59.dist-info/RECORD
