Metadata-Version: 2.1
Name: bcsfe-discord
Version: 2.7.59
Summary: BCSFE_Python personal api
Home-page: 
Author: CintagramABP
Requires-Python: >=3.9
Requires-Dist: colored ==1.4.4
Requires-Dist: tk
Requires-Dist: python-dateutil
Requires-Dist: requests
Requires-Dist: pyyaml
Requires-Dist: aiohttp
Provides-Extra: testing
Requires-Dist: pytest ; extra == 'testing'
Requires-Dist: pytest-cov ; extra == 'testing'
